{
	"version": "1.2",
	"title": "PHYS 342",
	"subtitle": "Modern Physics",
	"logo": "logo.png",
	"department": "Department of Physics and Astronomy",
	"unit": [
		{
			"id": "lecture",
			"name": "Lecture",
			"base": true
		},
		{
			"id": "unit",
			"name": "Unit"
		},
		{
			"id": "week",
			"name": "Week",
			"default": true
		},
		{
			"id": "test",
			"name": "Test"
		}
	],
	"question": [
		{
			"id": "Q01.01.1",
			"lecture": [
				1
			],
			"unit": [
				1
			],
			"week": [
				1
			],
			"test": [
				1
			],
			"vignette": [
				{
					"type": "text",
					"content": "The laws of nature"
				}
			],
			"answer": [
				{
					"type": "text",
					"correct": false,
					"content": "always agree with common sense"
				},
				{
					"type": "text",
					"correct": true,
					"content": "often have nothing to do with common sense"
				},
				{
					"type": "text",
					"correct": false,
					"content": "never agree with common sense"
				}
			]
		},
		{
			"id": "Q01.01.2",
			"lecture": [
				1
			],
			"unit": [
				1
			],
			"week": [
				1
			],
			"test": [
				1
			],
			"vignette": [
				{
					"type": "text",
					"content": "The rise of what we often call “modern physics” began"
				}
			],
			"answer": [
				{
					"type": "text",
					"correct": false,
					"content": "in the late 1600s"
				},
				{
					"type": "text",
					"correct": false,
					"content": "in the late 1700s"
				},
				{
					"type": "text",
					"correct": true,
					"content": "in the late 1800s"
				}
			]
		},
		{
			"id": "Q01.01.3",
			"lecture": [
				1
			],
			"unit": [
				1
			],
			"week": [
				1
			],
			"test": [
				1
			],
			"vignette": [
				{
					"type": "text",
					"content": "Which of the following statements is closest to being true?"
				}
			],
			"answer": [
				{
					"type": "text",
					"correct": false,
					"content": "Aristotle tended to emphasize experiment while Galileo tended to emphasize reason."
				},
				{
					"type": "text",
					"correct": false,
					"content": "Both Aristotle and Galileo tended to emphasize reason over experiment."
				},
				{
					"type": "text",
					"correct": true,
					"content": "Aristotle tended to emphasize reason while Galileo tended to emphasize experiment."
				}
			]
		},
		{
			"id": "Q01.01.4",
			"lecture": [
				1
			],
			"unit": [
				1
			],
			"week": [
				1
			],
			"test": [
				1
			],
			"vignette": [
				{
					"type": "text",
					"content": "The US National Academy of Engineering is periodically tasked with identifying Grand Challenges in Engineering. Which of the following statements is closest to being true?"
				}
			],
			"answer": [
				{
					"type": "text",
					"correct": true,
					"content": "Many of the challenging engineering problems identified by the US Academy will require quantum physics to solve."
				},
				{
					"type": "text",
					"correct": false,
					"content": "None of the challenging engineering problems identified by the US Academy will require quantum physics to solve."
				},
				{
					"type": "text",
					"correct": false,
					"content": "All of the challenging engineering problems identified by the US Academy will require quantum physics to solve."
				}
			]
		},
		{
			"id": "Q01.02.1",
			"lecture": [
				2
			],
			"unit": [
				2
			],
			"week": [
				1
			],
			"test": [
				1
			],
			"vignette": [
				{
					"type": "text",
					"content": "The potential energy that a particle has at a point P in space"
				}
			],
			"answer": [
				{
					"type": "text",
					"correct": true,
					"content": "measures the work required to move it to point P"
				},
				{
					"type": "text",
					"correct": false,
					"content": "goes to zero exponentially with time"
				},
				{
					"type": "text",
					"correct": false,
					"content": "depends on how fast you move it to point P"
				}
			]
		},
		{
			"id": "Q01.02.2",
			"lecture": [
				2
			],
			"unit": [
				2
			],
			"week": [
				1
			],
			"test": [
				1
			],
			"vignette": [
				{
					"type": "text",
					"content": "Noether’s theorem states that"
				}
			],
			"answer": [
				{
					"type": "text",
					"correct": false,
					"content": "a change in kinetic energy of a mass is related to the work done on the mass"
				},
				{
					"type": "text",
					"correct": false,
					"content": "only changes in potential energy are relevant to predicting motion of a point mass"
				},
				{
					"type": "text",
					"correct": true,
					"content": "a conservation law implies an underlying symmetry"
				}
			]
		},
		{
			"id": "Q01.02.3",
			"lecture": [
				2
			],
			"unit": [
				2
			],
			"week": [
				1
			],
			"test": [
				1
			],
			"vignette": [
				{
					"type": "text",
					"content": "An important property of wave motion is that"
				}
			],
			"answer": [
				{
					"type": "text",
					"correct": false,
					"content": "two waves cannot be at the same place at the same time"
				},
				{
					"type": "text",
					"correct": true,
					"content": "two waves can be at the same place at the same time"
				},
				{
					"type": "text",
					"correct": false,
					"content": "two waves can be at the same place but at different times"
				}
			]
		},
		{
			"id": "Q01.02.4",
			"lecture": [
				2
			],
			"unit": [
				2
			],
			"week": [
				1
			],
			"test": [
				1
			],
			"vignette": [
				{
					"type": "text",
					"content": "A negative charge is suspended above a uniform sheet of positive charge which has lateral dimensions L x L, as shown. The electrostatic potential energy will be a minimum when"
				},
				{
					"type": "image",
					"content": "Q01.02.4/image1.png"
				}
			],
			"answer": [
				{
					"type": "text",
					"correct": false,
					"content": "the negative charge is a large distance from the charged sheet "
				},
				{
					"type": "text",
					"correct": false,
					"content": "the negative charge is at a fixed distance L from the charged sheet"
				},
				{
					"type": "text",
					"correct": true,
					"content": "the negative charge is as close as possible to the charged sheet "
				}
			]
		},
		{
			"id": "Q01.02.5",
			"lecture": [
				2
			],
			"unit": [
				2
			],
			"week": [
				1
			],
			"test": [
				1
			],
			"vignette": [
				{
					"type": "text",
					"content": "Wave motion is"
				}
			],
			"answer": [
				{
					"type": "text",
					"correct": false,
					"content": "described by a first order differential equation"
				},
				{
					"type": "text",
					"correct": true,
					"content": "described by a second order differential equation"
				},
				{
					"type": "text",
					"correct": false,
					"content": "described by a third order differential equation"
				}
			]
		}
	]
}